marquetry/__init__.py
marquetry/configuration.py
marquetry/container.py
marquetry/cuda_backend.py
marquetry/dataset.py
marquetry/function.py
marquetry/layer.py
marquetry/machine_learning.py
marquetry/model.py
marquetry/optimizer.py
marquetry/preprocess.py
marquetry/dataloaders/__init__.py
marquetry/dataloaders/dataloader.py
marquetry/dataloaders/sequence_dataloader.py
marquetry/datasets/__init__.py
marquetry/datasets/csv_loader.py
marquetry/datasets/fashion_mnist.py
marquetry/datasets/mnist.py
marquetry/datasets/spiral.py
marquetry/datasets/titanic.py
marquetry/datasets/trigonometric_curve.py
marquetry/functions/__init__.py
marquetry/functions/activations/__init__.py
marquetry/functions/activations/gelu.py
marquetry/functions/activations/glu.py
marquetry/functions/activations/identity.py
marquetry/functions/activations/leaky_relu.py
marquetry/functions/activations/log_softmax.py
marquetry/functions/activations/mish.py
marquetry/functions/activations/prelu.py
marquetry/functions/activations/relu.py
marquetry/functions/activations/sigmoid.py
marquetry/functions/activations/softmax.py
marquetry/functions/activations/softplus.py
marquetry/functions/activations/swish.py
marquetry/functions/activations/tanh.py
marquetry/functions/array/__init__.py
marquetry/functions/array/broadcast_to.py
marquetry/functions/array/col2im.py
marquetry/functions/array/concat.py
marquetry/functions/array/flatten.py
marquetry/functions/array/get_item.py
marquetry/functions/array/im2col.py
marquetry/functions/array/repeat.py
marquetry/functions/array/reshape.py
marquetry/functions/array/split.py
marquetry/functions/array/squeeze.py
marquetry/functions/array/sum_to.py
marquetry/functions/array/transpose.py
marquetry/functions/array/unsqueeze.py
marquetry/functions/connection/__init__.py
marquetry/functions/connection/convolution_2d.py
marquetry/functions/connection/convolution_2d_grad_w.py
marquetry/functions/connection/deconvolution_2d.py
marquetry/functions/connection/linear.py
marquetry-0.2.0.dist-info/LICENSE.md
marquetry-0.2.0.dist-info/METADATA
marquetry-0.2.0.dist-info/WHEEL
marquetry-0.2.0.dist-info/top_level.txt
marquetry-0.2.0.dist-info/RECORD
