Metadata-Version: 2.1
Name: marquetry
Version: 0.2.0
Summary: Simple Machine Learning Framework
Home-page: https://github.com/little-tabby/Marquetry
Download-URL: https://github.com/little-tabby/Marquetry
Author: SHIMA
Author-email: shima@little-tabby.com
Maintainer: Little Tabby
Maintainer-email: engineer@little-tabby.com
License: MIT
Keywords: deeplearning ml neuralnetwork
Classifier: Programming Language :: Python :: 3.8
Classifier: License :: OSI Approved :: MIT License
Classifier: Operating System :: OS Independent
Requires-Python: >=3.8
License-File: LICENSE.md
Requires-Dist: numpy >=1.20.0
Requires-Dist: pandas >=1.5.0
Requires-Dist: Pillow >=9.2.0
Requires-Dist: scipy >=1.0.0
